AUTHORS.rst
MANIFEST.in
README.md
requirements.txt
setup.cfg
setup.py
multidefusion/__init__.py
multidefusion/datainterface.py
multidefusion/fusion.py
multidefusion/integration.py
multidefusion/results.py
multidefusion.egg-info/PKG-INFO
multidefusion.egg-info/SOURCES.txt
multidefusion.egg-info/dependency_links.txt
multidefusion.egg-info/not-zip-safe
multidefusion.egg-info/top_level.txt
tests/test_multidefusion.py