Metadata-Version: 2.1
Name: multidefusion
Version: 0.0.16
Summary: Perform data fusion and analysis of the ground deformations for multiple stations.
Home-page: https://github.com/damiantondas/multidefusion
Author: Damian Tondas
Author-email: damian.tondas@gmail.com
License: MIT license
Keywords: multidefusion
Classifier: Intended Audience :: Developers
Classifier: License :: OSI Approved :: MIT License
Classifier: Natural Language :: English
Classifier: Programming Language :: Python :: 3
Classifier: Programming Language :: Python :: 3.8
Classifier: Programming Language :: Python :: 3.9
Classifier: Programming Language :: Python :: 3.10
Classifier: Programming Language :: Python :: 3.11
Requires-Python: >=3.8
License-File: AUTHORS.rst
